multiagent_testing/__init__.py
multiagent_testing/cli.py
multiagent_testing-1.0.1.dist-info/METADATA
multiagent_testing-1.0.1.dist-info/WHEEL
multiagent_testing-1.0.1.dist-info/entry_points.txt
multiagent_testing-1.0.1.dist-info/top_level.txt
multiagent_testing-1.0.1.dist-info/RECORD
