Metadata-Version: 2.4
Name: multiagent-testing
Version: 1.0.1
Summary: Multi-agent testing framework with GitHub integration
Project-URL: Homepage, https://github.com/vanman2024/multiagent-testing
Project-URL: Issues, https://github.com/vanman2024/multiagent-testing/issues
Classifier: Development Status :: 3 - Alpha
Classifier: Intended Audience :: Developers
Classifier: License :: OSI Approved :: MIT License
Classifier: Programming Language :: Python :: 3
Classifier: Programming Language :: Python :: 3.8
Classifier: Programming Language :: Python :: 3.9
Classifier: Programming Language :: Python :: 3.10
Classifier: Programming Language :: Python :: 3.11
Classifier: Programming Language :: Python :: 3.12
Requires-Python: >=3.8
Requires-Dist: multiagent-core>=0.1.0
Requires-Dist: click>=8.0.0
Requires-Dist: rich>=10.0.0
Requires-Dist: pytest>=7.0.0
Requires-Dist: playwright>=1.30.0
Requires-Dist: requests>=2.28.0
